{
  "name": "DevStat — Medical Statistics Software",
  "image": "mcr.microsoft.com/devcontainers/python:3.11",
  "features": {
    "ghcr.io/devcontainers/features/node:1": {
      "version": "20"
    }
  },
  "postCreateCommand": "bash .devcontainer/setup.sh",
  "postStartCommand": "bash codespace_setup/start.sh",
  "forwardPorts": [8150],
  "portsAttributes": {
    "8150": {
      "label": "DevStat App",
      "onAutoForward": "openBrowser"
    }
  },
  "customizations": {
    "vscode": {
      "extensions": [
        "ms-python.python",
        "ms-python.vscode-pylance",
        "dbaeumer.vscode-eslint",
        "esbenp.prettier-vscode"
      ],
      "settings": {
        "python.defaultInterpreterPath": "backend/venv/bin/python"
      }
    }
  }
}
